indexor/__init__.py
indexor/indexor.py
indexor-0.1.1.dist-info/LICENSE.txt
indexor-0.1.1.dist-info/METADATA
indexor-0.1.1.dist-info/WHEEL
indexor-0.1.1.dist-info/top_level.txt
indexor-0.1.1.dist-info/RECORD
