Metadata-Version: 2.1
Name: indexor
Version: 0.1.1
Summary: The best indexor
Home-page: https://github.com/kpedrozag/myfirstpkg
Author: Kevin Pedroza Goenaga
Author-email: kevinpedroza26@gmail.com
License: GNU GPLv3
Keywords: print indexor message
Platform: UNKNOWN
Classifier: Programming Language :: Python :: 3
Classifier: License :: OSI Approved :: MIT License
Classifier: Operating System :: OS Independent
